omop2fhir_vocab/__init__.py
omop2fhir_vocab/__main__.py
omop2fhir_vocab/omop2fhir_vocab.py
omop2fhir_vocab-1.1.6.dist-info/LICENSE
omop2fhir_vocab-1.1.6.dist-info/METADATA
omop2fhir_vocab-1.1.6.dist-info/WHEEL
omop2fhir_vocab-1.1.6.dist-info/entry_points.txt
omop2fhir_vocab-1.1.6.dist-info/top_level.txt
omop2fhir_vocab-1.1.6.dist-info/RECORD
