Metadata-Version: 2.1
Name: omop2fhir-vocab
Version: 1.1.6
Summary: Convert OMOP vocab to FHIR.
Home-page: https://github.com/HOT-Ecosystem/omop2fhir-vocab
Author: Joe Flack
Author-email: jflack@jhu.edu
Classifier: License :: OSI Approved :: MIT License
Classifier: Programming Language :: Python
Classifier: Programming Language :: Python :: 3
Classifier: Programming Language :: Python :: 3.9
Classifier: Programming Language :: Python :: 3.10
Classifier: Programming Language :: Python :: 3.11
Classifier: Programming Language :: Python :: 3.12
Classifier: Programming Language :: Python :: Implementation :: CPython
Classifier: Programming Language :: Python :: Implementation :: PyPy
Requires-Python: >=3.9.0
License-File: LICENSE
Requires-Dist: omop2owl-vocab >=1.3.5
Requires-Dist: owl-on-fhir >=1.1.1
